wavcheck/__init__.py
wavcheck/__main__.py
wavcheck/check.py
wavcheck/data.py
wavcheck/fix.py
wavcheck/main.py
wavcheck/print.py
wavcheck/prompt.py
wavcheck/read.py
wavcheck/report.py
wavcheck/test_timecode.py
wavcheck/timecode.py
wavcheck/write.py
wavcheck-0.9.4.dist-info/METADATA
wavcheck-0.9.4.dist-info/WHEEL
wavcheck-0.9.4.dist-info/entry_points.txt
wavcheck-0.9.4.dist-info/top_level.txt
wavcheck-0.9.4.dist-info/RECORD
