Metadata-Version: 2.1
Name: wavcheck
Version: 0.9.4
Summary: Check WAV files for Broadcast Wave Format issues
Home-page: https://github.com/barndollarmusic/wavcheck
Author: Barndollar Music, Ltd.
Author-email: eric@barndollarmusic.com
Project-URL: Bug Tracker, https://github.com/barndollarmusic/wavcheck/issues
Classifier: Programming Language :: Python :: 3
Classifier: License :: OSI Approved :: Apache Software License
Classifier: Operating System :: OS Independent
Requires-Python: >=3.6
Requires-Dist: colorama >=0.4.4
